{
  "version": "vplot-0.1",
  "dataset": {
    "name": "weather.csv",
    "hash": "sha256:2153126325ca72cffbff3adb0993f732268f0012d65195ffeb27d17d8d70dc08"
  },
  "transform": [
    {
      "op": "select",
      "fields": [
        "date",
        "city",
        "temp_c"
      ]
    }
  ],
  "mark": "line",
  "encoding": {
    "x": {
      "field": "date",
      "type": "temporal"
    },
    "y": {
      "field": "temp_c",
      "type": "quantitative"
    },
    "color": {
      "field": "city",
      "type": "nominal"
    }
  }
}
